MANIFEST.in
README.rst
setup.py
makeCourse/Session.py
makeCourse/StrLang.py
makeCourse/__init__.py
makeCourse/config.py
makeCourse/examples.py
makeCourse/makeCourse.py
makeCourse/mkcException.py
makeCourse/osUtils.py
makeCourse/wordpress.py
makeCourse.egg-info/PKG-INFO
makeCourse.egg-info/SOURCES.txt
makeCourse.egg-info/dependency_links.txt
makeCourse.egg-info/not-zip-safe
makeCourse.egg-info/requires.txt
makeCourse.egg-info/top_level.txt